py2png.py
py2png-0.1.1.dist-info/DESCRIPTION.rst
py2png-0.1.1.dist-info/METADATA
py2png-0.1.1.dist-info/RECORD
py2png-0.1.1.dist-info/WHEEL
py2png-0.1.1.dist-info/entry_points.txt
py2png-0.1.1.dist-info/metadata.json
py2png-0.1.1.dist-info/top_level.txt
